airflow_aggua_plugin/__init__.py
airflow_aggua_plugin/config.py
airflow_aggua_plugin/main.py
airflow_aggua_plugin/utils.py
airflow_aggua_plugin/api/__init__.py
airflow_aggua_plugin/api/api_setup.py
airflow_aggua_plugin/api/app.py
airflow_aggua_plugin/api/response.py
airflow_aggua_plugin/api/endpoints/__init__.py
airflow_aggua_plugin/api/endpoints/get_serialized_dags.py
airflow_aggua_plugin/api/schemas/__init__.py
airflow_aggua_plugin/api/schemas/serialized_dag_schema.py
airflow_aggua_plugin/ui/__init__.py
airflow_aggua_plugin/ui/app_builder_view.py
airflow_aggua_plugin/ui/docs.py
airflow_aggua_plugin/ui/static/css/main.css
airflow_aggua_plugin/ui/static/js/main.js
airflow_aggua_plugin/ui/templates/doc_body.jinja.html
airflow_aggua_plugin/ui/templates/doc_head.jinja.html
airflow_aggua_plugin/ui/templates/doc_index.jinja.html
airflow_aggua_plugin-1.0.8.dist-info/LICENSE
airflow_aggua_plugin-1.0.8.dist-info/METADATA
airflow_aggua_plugin-1.0.8.dist-info/WHEEL
airflow_aggua_plugin-1.0.8.dist-info/entry_points.txt
airflow_aggua_plugin-1.0.8.dist-info/top_level.txt
airflow_aggua_plugin-1.0.8.dist-info/RECORD
